tt_tui/__init__.py
tt_tui/api.py
tt_tui/app.py
tt_tui/models.py
tt_tui/monitor.py
tt_tui/ssh_tunnel.py
tt_tui/screens/__init__.py
tt_tui/widgets/__init__.py
tt_tui/widgets/entrypoints.py
tt_tui/widgets/info.py
tt_tui/widgets/middlewares.py
tt_tui/widgets/profile_editor.py
tt_tui/widgets/profile_list.py
tt_tui/widgets/routers.py
tt_tui/widgets/services.py
tt_tui/widgets/status_bar.py
tt_tui_for_traefik-0.1.3.dist-info/METADATA
tt_tui_for_traefik-0.1.3.dist-info/WHEEL
tt_tui_for_traefik-0.1.3.dist-info/entry_points.txt
tt_tui_for_traefik-0.1.3.dist-info/licenses/LICENSE.txt
tt_tui_for_traefik-0.1.3.dist-info/RECORD
