Metadata-Version: 2.4
Name: tt-tui-for-traefik
Version: 0.1.3
Summary: A TUI dashboard for Traefik
License-Expression: MIT
License-File: LICENSE.txt
Requires-Python: >=3.11
Requires-Dist: asyncssh>=2.14.0
Requires-Dist: httpx>=0.28.0
Requires-Dist: pydantic>=2.0.0
Requires-Dist: textual>=0.89.0
Requires-Dist: tomli-w>=1.0.0
Requires-Dist: tomli>=2.0.0
Provides-Extra: dev
Requires-Dist: pytest>=8.0.0; extra == 'dev'
Requires-Dist: ruff>=0.8.0; extra == 'dev'
Requires-Dist: textual-dev>=1.0.0; extra == 'dev'
